.gitignore
README.rst
base.cfg
bootstrap.py
buildout.cfg
minitage-buildout.cfg
minitage-test-4.0.x.cfg
minitage-test-4.1.x.cfg
minitage-test-4.2.x.cfg
minitage.cfg
setup.cfg
setup.py
test-4.0.x.cfg
test-4.1.x.cfg
test-4.2.x.cfg
version.txt
Products.RefBiblioParser-minilay/Products.RefBiblioParser
Products.RefBiblioParser-minilay/Products.RefBiblioParser-p40
Products.RefBiblioParser-minilay/Products.RefBiblioParser-p41
Products.RefBiblioParser-minilay/Products.RefBiblioParser-p42
docs/CHANGES.rst
docs/INSTALL.rst
docs/LICENSE.GPL
docs/LICENSE.txt
scripts/sync_from_generic.sh
seleniums/refbiblioparser.selenium
src/__init__.py
src/Products/__init__.py
src/Products.RefBiblioParser.egg-info/PKG-INFO
src/Products.RefBiblioParser.egg-info/SOURCES.txt
src/Products.RefBiblioParser.egg-info/dependency_links.txt
src/Products.RefBiblioParser.egg-info/entry_points.txt
src/Products.RefBiblioParser.egg-info/namespace_packages.txt
src/Products.RefBiblioParser.egg-info/requires.txt
src/Products.RefBiblioParser.egg-info/top_level.txt
src/Products/RefBiblioParser/RefParser.py
src/Products/RefBiblioParser/RefRenderer.py
src/Products/RefBiblioParser/__init__.py
src/Products/RefBiblioParser/app_config.py
src/Products/RefBiblioParser/configure.zcml
src/Products/RefBiblioParser/dashboard.py
src/Products/RefBiblioParser/interfaces.py
src/Products/RefBiblioParser/profiles.zcml
src/Products/RefBiblioParser/rebuild_i18n.sh
src/Products/RefBiblioParser/setuphandlers.py
src/Products/RefBiblioParser/testing.py
src/Products/RefBiblioParser/version.txt
src/Products/RefBiblioParser/Extensions/__init__.py
src/Products/RefBiblioParser/browser/__init__.py
src/Products/RefBiblioParser/browser/configure.zcml
src/Products/RefBiblioParser/browser/template.pt
src/Products/RefBiblioParser/browser/view.py
src/Products/RefBiblioParser/browser/viewlet.pt
src/Products/RefBiblioParser/browser/viewlets.py
src/Products/RefBiblioParser/browser/resources/README.txt
src/Products/RefBiblioParser/locales/Products.RefBiblioParser-manual.pot
src/Products/RefBiblioParser/locales/Products.RefBiblioParser.pot
src/Products/RefBiblioParser/locales/fr/LC_MESSAGES/Products.RefBiblioParser.po
src/Products/RefBiblioParser/migrations/__init__.py
src/Products/RefBiblioParser/migrations/configure.zcml
src/Products/RefBiblioParser/migrations/v11/__init__.py
