Metadata-Version: 1.0
Name: Products.RefBiblioParser
Version: 1.0
Summary: Project %s
Home-page: http://pypi.python.org/pypi/Products.RefBiblioParser
Author: kiorky
Author-email: kiorky@cryptelium.net
License: GPL
Keywords: ref biblio parser
Platform: UNKNOWN
Classifier: Framework :: Plone
Classifier: Framework :: Plone :: 4.0
Classifier: Framework :: Plone :: 4.1
Classifier: Framework :: Plone :: 4.2
Classifier: Programming Language :: Python
Classifier: Topic :: Software Development
